datclass/__init__.py
foyou_datclass-0.0.5.dist-info/LICENSE
foyou_datclass-0.0.5.dist-info/METADATA
foyou_datclass-0.0.5.dist-info/WHEEL
foyou_datclass-0.0.5.dist-info/entry_points.txt
foyou_datclass-0.0.5.dist-info/top_level.txt
foyou_datclass-0.0.5.dist-info/RECORD
