Metadata-Version: 2.1
Name: foyou-datclass
Version: 0.0.5
Summary: parse json to dataclass
Home-page: https://github.com/foyoux/foyou-datclass
Author: foyou
Author-email: yimi.0822@qq.com
License: GPL-3.0
Project-URL: Source, https://github.com/foyoux/foyou-datclass
Project-URL: Bug Tracker, https://github.com/foyoux/foyou-datclass/issues
Keywords: ring kugou
Platform: UNKNOWN
Classifier: Programming Language :: Python :: 3
Classifier: Programming Language :: Python :: 3.7
Classifier: Programming Language :: Python :: 3.8
Classifier: Programming Language :: Python :: 3.9
Classifier: Programming Language :: Python :: 3.10
Classifier: Programming Language :: Python :: 3.11
Classifier: License :: OSI Approved :: GNU General Public License v3 (GPLv3)
Classifier: Environment :: Console
Classifier: Natural Language :: Chinese (Simplified)
Classifier: Development Status :: 4 - Beta
Requires-Python: >=3.7.*
Requires-Dist: typing-extensions
Requires-Dist: case-convert
